carbgremover/__init__.py
carbgremover/external_model.py
carbgremover/internal_model.py
carbgremover/images/car1.jpg
carbgremover/images/car2.jpg
carbgremover/images/rescar1.jpg
carbgremover/images/rescar2.jpg
carbgremover/pretrained_models/best_model_weights.h5
carbgremover/pretrained_models/sam_vit_h_4b8939.pth
CarSegmentPro-0.0.1.dist-info/METADATA
CarSegmentPro-0.0.1.dist-info/WHEEL
CarSegmentPro-0.0.1.dist-info/top_level.txt
CarSegmentPro-0.0.1.dist-info/RECORD
