Metadata-Version: 2.1
Name: CarSegmentPro
Version: 0.0.1
Home-page: https://github.com/NechbaMohammed/CarSegmentPro
Author: ['Tawfiq Adnane', 'Mohammed Nechba']
Author-email: tawfiqaadnane@gmail.com
Maintainer-email: mohammednechba@gmail.com
Requires-Dist: opencv-python
Requires-Dist: numpy
Requires-Dist: tensorflow
Requires-Dist: ultralytics
Requires-Dist: segment-anything
Requires-Dist: tqdm
Requires-Dist: requests
